tuto_python_setup_package/__init__.py
tuto_python_setup_package/_version.py
tuto_python_setup_package/py.typed
tuto_python_setup_package/core/__init__.py
tuto_python_setup_package/utils/__init__.py
tuto_python_setup_package-0.1.0.dist-info/METADATA
tuto_python_setup_package-0.1.0.dist-info/WHEEL
tuto_python_setup_package-0.1.0.dist-info/RECORD
