Metadata-Version: 2.4
Name: tuto-python-setup-package
Version: 0.1.0
Summary: Tutorial package for Python setup workflow
Author-email: Gabriel Jarry <jarry.gabriel@gmail.com>
License: MIT
Classifier: Development Status :: 3 - Alpha
Classifier: License :: OSI Approved :: MIT License
Classifier: Programming Language :: Python :: 3.12
Classifier: Programming Language :: Python :: 3.13
Classifier: Typing :: Typed
Requires-Python: >=3.12
Requires-Dist: loguru>=0.7.3
Requires-Dist: pydantic-settings>=2.12.0
Requires-Dist: pydantic>=2.12.5
